[
  {
    "title": "A R R I V A L",
    "filename": "arrival.gif"
  },
  {
    "title": "D E P A R T U R E",
    "filename": "departure.gif"
  },
  {
    "title": "seal invasion",
    "filename": "seal-invasion.png"
  },
  {
    "title": "chonki seel blackdragon",
    "filename": "chonk.png"
  },
  {
    "title": ".NET developer lmfao",
    "filename": "dotnet-dev.png"
  },
  {
    "title": "little nap",
    "filename": "little-nap.jpeg"
  },
  {
    "title": "ralcat",
    "filename": "ralcat.jpeg"
  }
]
